<annotation>
	<folder></folder>
	<filename>84_jpg.rf.af23d6cff49d3c9fbd693dccee563aaf.jpg</filename>
	<path>84_jpg.rf.af23d6cff49d3c9fbd693dccee563aaf.jpg</path>
	<source>
		<database>roboflow.com</database>
	</source>
	<size>
		<width>320</width>
		<height>320</height>
		<depth>3</depth>
	</size>
	<segmented>0</segmented>
	<object>
		<name>license</name>
		<pose>Unspecified</pose>
		<truncated>0</truncated>
		<difficult>0</difficult>
		<occluded>0</occluded>
		<bndbox>
			<xmin>158</xmin>
			<xmax>213</xmax>
			<ymin>143</ymin>
			<ymax>176</ymax>
		</bndbox>
		<polygon>
			<x1>209.6875</x1>
			<y1>167.561042</y1>
			<x2>211.875</x2>
			<y2>165.47695</y2>
			<x3>211.25</x3>
			<y3>145.469661</y3>
			<x4>209.6875</x4>
			<y4>141.718295</y4>
			<x5>157.8125</x5>
			<y5>149.221028</y5>
			<x6>156.875</x6>
			<y6>155.473305</y6>
			<x7>159.0625</x7>
			<y7>175.063776</y7>
			<x8>209.6875</x8>
			<y8>167.561042</y8>
		</polygon>
	</object>
</annotation>
