<annotation>
	<folder></folder>
	<filename>k1g3b7tc8vna1_jpg.rf.71b04278a765c2e39d81bad0f122d68d.jpg</filename>
	<path>k1g3b7tc8vna1_jpg.rf.71b04278a765c2e39d81bad0f122d68d.jpg</path>
	<source>
		<database>roboflow.com</database>
	</source>
	<size>
		<width>320</width>
		<height>320</height>
		<depth>3</depth>
	</size>
	<segmented>0</segmented>
	<object>
		<name>license</name>
		<pose>Unspecified</pose>
		<truncated>0</truncated>
		<difficult>0</difficult>
		<occluded>0</occluded>
		<bndbox>
			<xmin>100</xmin>
			<xmax>163</xmax>
			<ymin>159</ymin>
			<ymax>205</ymax>
		</bndbox>
		<polygon>
			<x1>161.59</x1>
			<y1>163.713333</y1>
			<x2>102.485</x2>
			<y2>157.613333</y2>
			<x3>99.305</x3>
			<y3>198.473333</y3>
			<x4>158.805</x4>
			<y4>204.046667</y4>
			<x5>161.59</x5>
			<y5>163.713333</y5>
		</polygon>
	</object>
</annotation>
